npindex/__init__.py
npindex/index_generator.py
npindex-0.1.1.dist-info/WHEEL
npindex-0.1.1.dist-info/METADATA
npindex-0.1.1.dist-info/RECORD
