Metadata-Version: 2.1
Name: npindex
Version: 0.1.1
Summary: Provide an intuitive way to make ndarray indexing variable.
Home-page: https://github.com/kendimaru/npindex
License: MIT
Keywords: numpy,indexing,utility,slice
Author: kenjimaru
Author-email: kendimaru2@gmail.com
Maintainer: kenjimaru
Maintainer-email: kendimaru2@gmail.com
Requires-Python: >=3.6,<4.0
Classifier: Development Status :: 3 - Alpha
Classifier: Intended Audience :: Developers
Classifier: License :: OSI Approved :: MIT License
Classifier: Programming Language :: Python :: 3
Classifier: Programming Language :: Python :: 3.6
Classifier: Programming Language :: Python :: 3.7
Classifier: Programming Language :: Python :: 3.8
Classifier: Programming Language :: Python :: 3.9
Project-URL: Repository, https://github.com/kendimaru/npindex
